epydemic_signals/__init__.py
epydemic_signals/compartment_signal.py
epydemic_signals/hitting_healing.py
epydemic_signals/infection_boundary_signal.py
epydemic_signals/progress_signal.py
epydemic_signals/py.typed
epydemic_signals/signal.py
epydemic_signals/signaldynamics.py
epydemic_signals/signalgenerator.py
epydemic_signals/sir_healing.py
epydemic_signals/sir_healing_one.py
epydemic_signals/stochasticsignaldynamics.py
epydemic_signals/synchronoussignaldynamics.py
epydemic_signals/timeddict.py
epydemic_signals/plot/__init__.py
epydemic_signals/plot/plot_compartments.py
epydemic_signals/plot/plot_signal.py
epydemic_signals-0.1.1.dist-info/LICENSE
epydemic_signals-0.1.1.dist-info/METADATA
epydemic_signals-0.1.1.dist-info/WHEEL
epydemic_signals-0.1.1.dist-info/top_level.txt
epydemic_signals-0.1.1.dist-info/RECORD
