Metadata-Version: 2.1
Name: epydemic-signals
Version: 0.1.1
Summary: An experiment in spidemics as signals
Home-page: http://github.com/simoninireland/epydemic-signals
Author: Simon Dobson
Author-email: simoninireland@gmail.com
License: License :: OSI Approved :: GNU General Public License v3 (GPLv3)
Platform: UNKNOWN
Classifier: Development Status :: 2 - Pre-Alpha
Classifier: Intended Audience :: Science/Research
Classifier: Intended Audience :: Developers
Classifier: Programming Language :: Python :: 3.6
Classifier: Programming Language :: Python :: 3.7
Classifier: Programming Language :: Python :: 3.8
Classifier: Programming Language :: Python :: 3.9
Classifier: Programming Language :: Python :: 3.10
Classifier: Topic :: Scientific/Engineering
Requires-Python: >=3.6
License-File: LICENSE
Requires-Dist: epydemic (>=1.11.1)
Requires-Dist: networkx
Requires-Dist: pandas
Requires-Dist: pygsp
Requires-Dist: pyunlocbox
Requires-Dist: matplotlib
Requires-Dist: mypy
Requires-Dist: jedi
Requires-Dist: jedi-language-server
Requires-Dist: black
